datfid/__init__.py
datfid/client.py
datfid-0.1.19.dist-info/licenses/LICENSE
datfid-0.1.19.dist-info/METADATA
datfid-0.1.19.dist-info/WHEEL
datfid-0.1.19.dist-info/top_level.txt
datfid-0.1.19.dist-info/RECORD
