Metadata-Version: 2.4
Name: datfid
Version: 0.1.19
Summary: SDK to access the DATFID API hosted on Hugging Face Spaces
Author: DATFID
Author-email: igor.schapiro@datfid.com
License: MIT
Classifier: License :: OSI Approved :: MIT License
Classifier: Programming Language :: Python :: 3
Requires-Python: >=3.7
License-File: LICENSE
Requires-Dist: requests>=2.31.0
Requires-Dist: pandas>=1.0.1
Requires-Dist: numpy<2.1,>=1.22
Dynamic: author
Dynamic: author-email
Dynamic: classifier
Dynamic: description
Dynamic: description-content-type
Dynamic: license
Dynamic: license-file
Dynamic: requires-dist
Dynamic: requires-python
Dynamic: summary
